{
  "type": "Feature",
  "properties":
  {
    "venue": "Casa Teatro El Poblado",
    "event": "Fundacámara. Dúo de guitarras Arias-Suárez",
    "date": "2016-01-30 T 18:00:00",
    "capacity": "156",
    "occupation": "51",
    "event_genres": "camara",
    "lineup": "arias-suarez",
    "headliner": "arias-suarez",
    "city": "medellin"
  },
  "geometry": {
    "type": "Point",
    "coordinates": [-75.58072328567505, 6.18831537756351]
  }
}