{
  "type": "Feature",
  "properties":
  {
    "venue": "Casa Teatro El Poblado",
    "event": "Funcámara. Recital piano Blanca Uribe. Andrés Gómez.",
    "date": "2014-11-28 T 20:00:00",
    "capacity": "156",
    "occupation": "34",
    "event_genres": "instrumental",
    "lineup": "blanca_uribe",
    "headliner": "blanca_uribe",
    "city": "medellin"
  },
  "geometry": {
    "type": "Point",
    "coordinates": [-75.58072328567505, 6.18831537756351]
  }
}