{
  "type": "Feature",
  "properties":
  {
    "venue": "Casa Teatro El Poblado",
    "event": "Claudia Gómez.",
    "date": "2013-09-27 T 20:00:00",
    "capacity": "156",
    "occupation": "77",
    "event_genres": "cantautor",
    "lineup": "claudia_gomez",
    "headliner": "Claudia Gómez.",
    "city": "medellin"
  },
  "geometry": {
    "type": "Point",
    "coordinates": [-75.58072328567505, 6.18831537756351]
  }
}