{
  "type": "Feature",
  "properties":
  {
    "venue": "Casa Teatro El Poblado",
    "event": "Concierto Escuela de música El Poblado",
    "date": "2013-11-23 T 18:00:00",
    "capacity": "156",
    "occupation": "500 (3 funciones)",
    "event_genres": "camara",
    "lineup": "escuela_de_musica_el_poblado",
    "headliner": "Escuela de música El Poblado",
    "city": "medellin"
  },
  "geometry": {
    "type": "Point",
    "coordinates": [-75.58072328567505, 6.18831537756351]
  }
}