{
  "type": "FeatureCollection",
  "features": [
    {
      "type": "Feature",
      "properties": {
        "venue": "Buckel Bar",
        "event": "Guitarruidosis",
        "date": "2010-05-15",
        "capacity": "",
        "occupation": "",
        "lineup": "Milena, The_kurtis_band",
        "event_genres": "Pop, electro_rock",
        "link": "",
        "added_by": "antropomorfa",
        "founder": "",
        "headliner": "Guitarruidosis",
        "address": "",
        "start": "",
        "end": "",
        "other_events": "",
        "news": "",
        "twitter_followers": "",
        "city": "Medellin"
      },
      "geometry": {
        "type": "Point",
        "coordinates": [
          -75.56899666786194,
          6.209519593386433
        ]
      }
    },
    {
      "type": "Feature",
      "properties": {
        "venue": "Eslabon prendido",
        "event": "Guitarruidosis",
        "date": "2004-06-12",
        "capacity": 200,
        "occupation": 100,
        "lineup": "acid_purple,smoking_souls, deaklen",
        "event_genres": "grunge",
        "link": "",
        "added_by": "antropomorfa",
        "founder": "",
        "headliner": "Guitarruidosis",
        "address": "",
        "start": "",
        "end": "",
        "other_events": "",
        "news": "",
        "twitter_followers": "",
        "city": "Medellin"
      },
      "geometry": {
        "type": "Point",
        "coordinates": [
          -75.56132555007935,
          6.249008567477176
        ]
      }
    }
  ]
}