{
  "type": "Feature",
  "properties":
  {
    "venue": "Casa Teatro El Poblado",
    "event": "La boca rota. Lanzamiento",
    "date": "2015-05-21 T 20:00:00",
    "capacity": "156",
    "occupation": "113",
    "event_genres": "",
    "lineup": "la_boca_rota",
    "headliner": "la_boca_rota",
    "city": "medellin"
  },
  "geometry": {
    "type": "Point",
    "coordinates": [-75.58072328567505, 6.18831537756351]
  }
}