{
  "type": "Feature",
  "properties":
  {
    "venue": "Casa Teatro El Poblado",
    "event": "Recital marimba. Miguel García Moreno",
    "date": "2015-11-24 T 20:00:00",
    "capacity": "156",
    "occupation": "58",
    "event_genres": "instrumental",
    "lineup": "miguel_garcía_moreno",
    "headliner": "miguel_garcía_moreno",
    "city": "medellin"
  },
  "geometry": {
    "type": "Point",
    "coordinates": [-75.58072328567505, 6.18831537756351]
  }
}