{
  "type": "Feature",
  "properties":
  {
    "venue": "Casa Teatro El Poblado",
    "event": "Festival clarisax",
    "date": "2014-03-22 T 10:00:00",
    "capacity": "156",
    "occupation": "231",
    "event_genres": "sinfonico",
    "lineup": "trio_instrumental_universidad_de_caldas",
    "headliner": "trio_instrumental_universidad_de_caldas",
    "city": "medellin"
  },
  "geometry": {
    "type": "Point",
    "coordinates": [-75.58072328567505, 6.18831537756351]
  }
}