{
  "type": "Feature",
  "properties":
  {
    "venue": "Casa Teatro El Poblado",
    "event": "Música Corriente. Uh la lá",
    "date": "2015-10-30 T 20:00:00",
    "capacity": "156",
    "occupation": "77",
    "event_genres": "",
    "lineup": "uh_la_lá",
    "headliner": "uh_la_lá",
    "city": "medellin"
  },
  "geometry": {
    "type": "Point",
    "coordinates": [-75.58072328567505, 6.18831537756351]
  }
}